TreeAVL/AVL.py
TreeAVL/__init__.py
Py_AVL_Tree-0.0.2.dist-info/LICENSE
Py_AVL_Tree-0.0.2.dist-info/METADATA
Py_AVL_Tree-0.0.2.dist-info/WHEEL
Py_AVL_Tree-0.0.2.dist-info/top_level.txt
Py_AVL_Tree-0.0.2.dist-info/RECORD
